{
  "parent": "minecraft:recipes/root",
  "criteria": {
    "has_processor": {
      "conditions": {
        "items": [
          {
            "items": [
              "refinedstorage:advanced_processor"
            ]
          }
        ]
      },
      "trigger": "minecraft:inventory_changed"
    },
    "has_the_recipe": {
      "conditions": {
        "recipe": "extradisks:advanced_storage_housing"
      },
      "trigger": "minecraft:recipe_unlocked"
    }
  },
  "requirements": [
    [
      "has_processor",
      "has_the_recipe"
    ]
  ],
  "rewards": {
    "recipes": [
      "extradisks:advanced_storage_housing"
    ]
  },
  "sends_telemetry_event": false
}